dharsh_mantis-0.1.0.dist-info/licenses/LICENSE
terminal_mantis/__init__.py
terminal_mantis/main.py
terminal_mantis/animations/mantis.animation
dharsh_mantis-0.1.0.dist-info/METADATA
dharsh_mantis-0.1.0.dist-info/WHEEL
dharsh_mantis-0.1.0.dist-info/entry_points.txt
dharsh_mantis-0.1.0.dist-info/top_level.txt
dharsh_mantis-0.1.0.dist-info/RECORD
