Metadata-Version: 2.4
Name: dharsh-mantis
Version: 0.1.0
Summary: Animated praying mantis for your terminal
Author-email: Dharsini Sri <purpleunalome@gmail.com>
License-Expression: MIT
Requires-Python: >=3.7
License-File: LICENSE
Dynamic: license-file
